sphinxhypothesis/__init__.py
sphinxhypothesis/extension.py
sphinxhypothesis/sphinxhypothesis.py
sphinx_hypothesis-0.1.0.dist-info/AUTHORS.rst
sphinx_hypothesis-0.1.0.dist-info/LICENSE
sphinx_hypothesis-0.1.0.dist-info/METADATA
sphinx_hypothesis-0.1.0.dist-info/WHEEL
sphinx_hypothesis-0.1.0.dist-info/top_level.txt
sphinx_hypothesis-0.1.0.dist-info/RECORD
