Metadata-Version: 2.1
Name: sphinx-hypothesis
Version: 0.1.0
Summary: sphinx-hypothesis enables https://web.hypothes.is/ in your Sphinx documentation
Home-page: https://github.com/humitos/sphinx-hypothesis
Author: Manuel Kaufmann
Author-email: humitos@gmail.com
License: MIT license
Keywords: sphinx hypothesis
Platform: UNKNOWN
Classifier: Development Status :: 2 - Pre-Alpha
Classifier: Intended Audience :: Developers
Classifier: License :: OSI Approved :: MIT License
Classifier: Natural Language :: English
Classifier: Programming Language :: Python :: 3
Classifier: Programming Language :: Python :: 3.5
Classifier: Programming Language :: Python :: 3.6
Classifier: Programming Language :: Python :: 3.7
Classifier: Programming Language :: Python :: 3.8
Requires-Python: >=3.5
